data_mem.v
module data_mem (
    input  wire clk,
    input  wire we,
    input  wire [7:0] addr,
    input  wire [7:0] wd,
    output reg  [7:0] rd
);

    reg [7:0] mem [0:255];
    integer i;

    initial begin
        for (i = 0; i < 256; i = i + 1)
            mem[i] = 8'b0; // initialize memory
    end

    // Write on clock
    always @(posedge clk) begin
        if (we)
            mem[addr] <= wd;
    end

    // Combinational read: rd always has a value
    always @(*) begin
        rd = mem[addr];
    end

endmodule

alu.v
module alu (
    input  wire [7:0] a, b,
    input  wire [3:0] alu_op,
    output reg  [7:0] result
);

    initial result = 8'b0; // initialize ALU result

    always @(*) begin
        case(alu_op)
            4'b0001: result = a + b;
            4'b0010: result = a - b;
            default: result = 8'b0;
        endcase
    end

endmodule

register_file.v
module register_file (
    input  wire clk,
    input  wire we,              
    input  wire [1:0] ra1, ra2,  
    input  wire [1:0] wa,        
    input  wire [7:0] wd,        
    output reg [7:0] rd1, rd2,   
    output [7:0] r0, r1, r2, r3  
);

    reg [7:0] regs [0:3];

    initial begin
        regs[0] = 8'b0;
        regs[1] = 8'b0;
        regs[2] = 8'b0;
        regs[3] = 8'b0;
    end

    always @(posedge clk) begin
        if (we)
            regs[wa] <= wd;
    end

    always @(*) begin
        rd1 = regs[ra1];
        rd2 = regs[ra2];
    end

    assign r0 = regs[0];
    assign r1 = regs[1];
    assign r2 = regs[2];
    assign r3 = regs[3];

endmodule

control_unit.v
module control_unit (
    input  wire [7:0] instruction,
    output wire [3:0] opcode,
    output wire [1:0] rd, rs1, rs2
);

    assign opcode = instruction[7:4];
    assign rd     = instruction[3:2];
    assign rs1    = instruction[1:0];
    assign rs2    = instruction[1:0]; // dummy for demo

endmodule

instruction_mem.v
module instruction_mem (
    input  wire [7:0] addr,
    output reg  [7:0] instruction
);

    reg [7:0] mem [0:255];

    integer i;
    initial begin
        for (i = 0; i < 256; i = i + 1)
            mem[i] = 8'b0; // initialize all instructions to 0

        // Example program (for demo)
        mem[0] = 8'b00010010;
        mem[1] = 8'b00100011;
        mem[2] = 8'b00011001;
    end

    always @(*) begin
        instruction = mem[addr];
    end

endmodule

pc.v
module pc (
    input  wire clk,
    input  wire reset,
    output reg [7:0] pc
);

    initial pc = 8'b0; // initialize PC to 0

    always @(posedge clk or posedge reset) begin
        if (reset)
            pc <= 8'b0;
        else
            pc <= pc + 1;
    end

endmodule

cpu_top.v
module cpu_top (
    input  wire clk,
    input  wire reset,
    output wire [7:0] pc_out,
    output wire [7:0] instr,
    output wire [7:0] rd1,
    output wire [7:0] rd2,
    output wire [7:0] alu_result,
    output wire [7:0] data_out,
    output wire [7:0] r0, r1, r2, r3
);

    wire [3:0] opcode;
    wire [1:0] rd, rs1, rs2;

    pc PC (.clk(clk), .reset(reset), .pc(pc_out));
    instruction_mem IM (.addr(pc_out), .instruction(instr));
    control_unit CU (.instruction(instr), .opcode(opcode), .rd(rd), .rs1(rs1), .rs2(rs2));
    register_file RF (
        .clk(clk), .we(1'b1),
        .ra1(rs1), .ra2(rs2), .wa(rd),
        .wd(alu_result),
        .rd1(rd1), .rd2(rd2),
        .r0(r0), .r1(r1), .r2(r2), .r3(r3)
    );
    alu ALU (.a(rd1), .b(rd2), .alu_op(opcode), .result(alu_result));
    data_mem DM (.clk(clk), .we(1'b0), .addr(alu_result), .wd(rd2), .rd(data_out));

endmodule

tb_cpu.v
`timescale 1ns/1ps
module tb_cpu;

    reg clk, reset;

    wire [7:0] pc_out, instr, rd1, rd2, alu_result, data_out;
    wire [7:0] r0, r1, r2, r3;

    cpu_top uut (
        .clk(clk),
        .reset(reset),
        .pc_out(pc_out),
        .instr(instr),
        .rd1(rd1),
        .rd2(rd2),
        .alu_result(alu_result),
        .data_out(data_out),
        .r0(r0), .r1(r1), .r2(r2), .r3(r3)
    );

    initial begin
        clk = 0;
        forever #5 clk = ~clk;
    end

    initial begin
        $dumpfile("cpu.vcd");
        $dumpvars(0, tb_cpu);

        reset = 1;
        #10 reset = 0;

        #200;
        $display("Simulation complete.");
        $finish;
    end

endmodule

cpu.vcd
$date
	Sat Sep 13 23:36:28 2025
$end
$version
	Icarus Verilog
$end
$timescale
	1ps
$end
$scope module tb_cpu $end
$var wire 8 ! rd2 [7:0] $end
$var wire 8 " rd1 [7:0] $end
$var wire 8 # r3 [7:0] $end
$var wire 8 $ r2 [7:0] $end
$var wire 8 % r1 [7:0] $end
$var wire 8 & r0 [7:0] $end
$var wire 8 ' pc_out [7:0] $end
$var wire 8 ( instr [7:0] $end
$var wire 8 ) data_out [7:0] $end
$var wire 8 * alu_result [7:0] $end
$var reg 1 + clk $end
$var reg 1 , reset $end
$scope module uut $end
$var wire 1 + clk $end
$var wire 1 , reset $end
$var wire 2 - rs2 [1:0] $end
$var wire 2 . rs1 [1:0] $end
$var wire 8 / rd2 [7:0] $end
$var wire 8 0 rd1 [7:0] $end
$var wire 2 1 rd [1:0] $end
$var wire 8 2 r3 [7:0] $end
$var wire 8 3 r2 [7:0] $end
$var wire 8 4 r1 [7:0] $end
$var wire 8 5 r0 [7:0] $end
$var wire 8 6 pc_out [7:0] $end
$var wire 4 7 opcode [3:0] $end
$var wire 8 8 instr [7:0] $end
$var wire 8 9 data_out [7:0] $end
$var wire 8 : alu_result [7:0] $end
$scope module ALU $end
$var wire 8 ; b [7:0] $end
$var wire 4 < alu_op [3:0] $end
$var wire 8 = a [7:0] $end
$var reg 8 > result [7:0] $end
$upscope $end
$scope module CU $end
$var wire 2 ? rs2 [1:0] $end
$var wire 2 @ rs1 [1:0] $end
$var wire 2 A rd [1:0] $end
$var wire 4 B opcode [3:0] $end
$var wire 8 C instruction [7:0] $end
$upscope $end
$scope module DM $end
$var wire 8 D addr [7:0] $end
$var wire 1 + clk $end
$var wire 1 E we $end
$var wire 8 F wd [7:0] $end
$var reg 8 G rd [7:0] $end
$var integer 32 H i [31:0] $end
$upscope $end
$scope module IM $end
$var wire 8 I addr [7:0] $end
$var reg 8 J instruction [7:0] $end
$var integer 32 K i [31:0] $end
$upscope $end
$scope module PC $end
$var wire 1 + clk $end
$var wire 1 , reset $end
$var reg 8 L pc [7:0] $end
$upscope $end
$scope module RF $end
$var wire 1 + clk $end
$var wire 8 M r0 [7:0] $end
$var wire 8 N r1 [7:0] $end
$var wire 8 O r2 [7:0] $end
$var wire 8 P r3 [7:0] $end
$var wire 2 Q ra1 [1:0] $end
$var wire 2 R ra2 [1:0] $end
$var wire 2 S wa [1:0] $end
$var wire 8 T wd [7:0] $end
$var wire 1 U we $end
$var reg 8 V rd1 [7:0] $end
$var reg 8 W rd2 [7:0] $end
$upscope $end
$upscope $end
$upscope $end
$enddefinitions $end
$comment Show the parameter values. $end
$dumpall
$end
#0
$dumpvars
b0 W
b0 V
1U
b0 T
b0 S
b10 R
b10 Q
b0 P
b0 O
b0 N
b0 M
b0 L
b100000000 K
b10010 J
b0 I
b100000000 H
b0 G
b0 F
0E
b0 D
b10010 C
b1 B
b0 A
b10 @
b10 ?
b0 >
b0 =
b1 <
b0 ;
b0 :
b0 9
b10010 8
b1 7
b0 6
b0 5
b0 4
b0 3
b0 2
b0 1
b0 0
b0 /
b10 .
b10 -
1,
0+
b0 *
b0 )
b10010 (
b0 '
b0 &
b0 %
b0 $
b0 #
b0 "
b0 !
$end
#5000
1+
#10000
0+
0,
#15000
b11 -
b11 ?
b11 R
b11 .
b11 @
b11 Q
b10 7
b10 <
b10 B
b100011 (
b100011 8
b100011 C
b100011 J
b1 '
b1 6
b1 I
b1 L
1+
#20000
0+
#25000
b1 -
b1 ?
b1 R
b1 .
b1 @
b1 Q
b10 1
b10 A
b10 S
b1 7
b1 <
b1 B
b11001 (
b11001 8
b11001 C
b11001 J
b10 '
b10 6
b10 I
b10 L
1+
#30000
0+
#35000
b0 -
b0 ?
b0 R
b0 .
b0 @
b0 Q
b0 1
b0 A
b0 S
b0 7
b0 <
b0 B
b0 (
b0 8
b0 C
b0 J
b11 '
b11 6
b11 I
b11 L
1+
#40000
0+
#45000
b100 '
b100 6
b100 I
b100 L
1+
#50000
0+
#55000
b101 '
b101 6
b101 I
b101 L
1+
#60000
0+
#65000
b110 '
b110 6
b110 I
b110 L
1+
#70000
0+
#75000
b111 '
b111 6
b111 I
b111 L
1+
#80000
0+
#85000
b1000 '
b1000 6
b1000 I
b1000 L
1+
#90000
0+
#95000
b1001 '
b1001 6
b1001 I
b1001 L
1+
#100000
0+
#105000
b1010 '
b1010 6
b1010 I
b1010 L
1+
#110000
0+
#115000
b1011 '
b1011 6
b1011 I
b1011 L
1+
#120000
0+
#125000
b1100 '
b1100 6
b1100 I
b1100 L
1+
#130000
0+
#135000
b1101 '
b1101 6
b1101 I
b1101 L
1+
#140000
0+
#145000
b1110 '
b1110 6
b1110 I
b1110 L
1+
#150000
0+
#155000
b1111 '
b1111 6
b1111 I
b1111 L
1+
#160000
0+
#165000
b10000 '
b10000 6
b10000 I
b10000 L
1+
#170000
0+
#175000
b10001 '
b10001 6
b10001 I
b10001 L
1+
#180000
0+
#185000
b10010 '
b10010 6
b10010 I
b10010 L
1+
#190000
0+
#195000
b10011 '
b10011 6
b10011 I
b10011 L
1+
#200000
0+
#205000
b10100 '
b10100 6
b10100 I
b10100 L
1+
